streamlit_math_keyboard/__init__.py
streamlit_math_keyboard/math_keyboard.py
streamlit_math_keyboard/frontend/build/index.html
streamlit_math_keyboard/frontend/build/assets/index.css
streamlit_math_keyboard/frontend/build/assets/index.js
streamlit_math_keyboard-0.1.1.dist-info/METADATA
streamlit_math_keyboard-0.1.1.dist-info/WHEEL
streamlit_math_keyboard-0.1.1.dist-info/top_level.txt
streamlit_math_keyboard-0.1.1.dist-info/RECORD
